visits/__init__.py
visits/admin.py
visits/apps.py
visits/middleware.py
visits/models.py
visits/tests.py
visits/views.py
visits/__pycache__/__init__.cpython-313.pyc
visits/__pycache__/admin.cpython-313.pyc
visits/__pycache__/apps.cpython-313.pyc
visits/__pycache__/middleware.cpython-313.pyc
visits/__pycache__/models.cpython-313.pyc
visits/locale/fa/LC_MESSAGES/django.mo
visits/locale/fa/LC_MESSAGES/django.po
visits/migrations/0001_initial.py
visits/migrations/__init__.py
visits/migrations/__pycache__/0001_initial.cpython-313.pyc
visits/migrations/__pycache__/__init__.cpython-313.pyc
django_dima_visits-1.3.dist-info/LICENSE
django_dima_visits-1.3.dist-info/METADATA
django_dima_visits-1.3.dist-info/WHEEL
django_dima_visits-1.3.dist-info/top_level.txt
django_dima_visits-1.3.dist-info/RECORD
