Metadata-Version: 2.2
Name: django-dima-visits
Version: 1.3
Summary: A simple Django app to track page visits for internal use.
Author: DIMACO
Author-email: dev@ddmc.ir
License: MIT
Classifier: Framework :: Django
Classifier: Programming Language :: Python :: 3
Classifier: Operating System :: OS Independent
Requires-Python: >=3.6
License-File: LICENSE
Requires-Dist: Django>=3.0
Dynamic: author
Dynamic: author-email
Dynamic: classifier
Dynamic: description
Dynamic: description-content-type
Dynamic: license
Dynamic: requires-dist
Dynamic: requires-python
Dynamic: summary
